sdgs_tools/__init__.py
sdgs_tools/__main__.py
sdgs_tools/aplikasi_sdgs/__init__.py
sdgs_tools/aplikasi_sdgs/export_individu/__init__.py
sdgs_tools/aplikasi_sdgs/export_individu/disabilitas.py
sdgs_tools/aplikasi_sdgs/export_individu/individu.py
sdgs_tools/aplikasi_sdgs/export_individu/kesehatan/__init__.py
sdgs_tools/aplikasi_sdgs/export_individu/kesehatan/fasilitas.py
sdgs_tools/aplikasi_sdgs/export_individu/kesehatan/penyakit.py
sdgs_tools/aplikasi_sdgs/export_individu/pekerjaan.py
sdgs_tools/aplikasi_sdgs/export_individu/pendidikan.py
sdgs_tools/aplikasi_sdgs/export_individu/penghasilan.py
sdgs_tools/aplikasi_sdgs/export_keluarga/__init__.py
sdgs_tools/aplikasi_sdgs/export_keluarga/kesehatan.py
sdgs_tools/aplikasi_sdgs/export_keluarga/lain_lain.py
sdgs_tools/aplikasi_sdgs/export_keluarga/lokasi.py
sdgs_tools/aplikasi_sdgs/export_keluarga/pendidikan.py
sdgs_tools/aplikasi_sdgs/export_keluarga/sarpras.py
sdgs_tools/aplikasi_sdgs/export_keluarga/tenaga_kesehatan.py
sdgs_tools/aplikasi_sdgs/utils.py
sdgs_tools/cli/__init__.py
sdgs_tools/cli/aplikasi/__init__.py
sdgs_tools/cli/aplikasi/export.py
sdgs_tools/cli/dashboard/__init__.py
sdgs_tools/cli/dashboard/individu.py
sdgs_tools/cli/dashboard/keluarga.py
sdgs_tools/cli/dashboard/template.py
sdgs_tools/cli/exporter.py
sdgs_tools/dashboard/__init__.py
sdgs_tools/dashboard/auth/__init__.py
sdgs_tools/dashboard/auth/base.py
sdgs_tools/dashboard/auth/token.py
sdgs_tools/dashboard/base.py
sdgs_tools/dashboard/edit_individu.py
sdgs_tools/dashboard/import_individu/__init__.py
sdgs_tools/dashboard/import_individu/data_individu.py
sdgs_tools/dashboard/import_individu/disabilitas.py
sdgs_tools/dashboard/import_individu/enums/__init__.py
sdgs_tools/dashboard/import_individu/enums/agama.py
sdgs_tools/dashboard/import_individu/enums/akses_internet.py
sdgs_tools/dashboard/import_individu/enums/diekspor.py
sdgs_tools/dashboard/import_individu/enums/jenis_kelamin.py
sdgs_tools/dashboard/import_individu/enums/kecepatan_internet.py
sdgs_tools-0.8.3.dist-info/entry_points.txt
sdgs_tools-0.8.3.dist-info/LICENSE
sdgs_tools-0.8.3.dist-info/WHEEL
sdgs_tools-0.8.3.dist-info/METADATA
sdgs_tools-0.8.3.dist-info/RECORD
