Metadata-Version: 2.1
Name: sdgs-tools
Version: 0.8.3
Summary: 
Home-page: https://github.com/hexatester/sdgs-tools
License: GPL-3.0-only
Keywords: sdgs,sdgs-dashboard,survey-sdgs,kemendesa
Author: hexatester
Author-email: hexatester@protonmail.com
Requires-Python: >=3.7.10,<4.0.0
Classifier: Development Status :: 4 - Beta
Classifier: Intended Audience :: Developers
Classifier: License :: OSI Approved :: GNU General Public License v3 (GPLv3)
Classifier: License :: OSI Approved :: MIT License
Classifier: Programming Language :: Python
Classifier: Programming Language :: Python :: 3
Classifier: Programming Language :: Python :: 3.7
Classifier: Programming Language :: Python :: 3.8
Classifier: Programming Language :: Python :: 3.9
Provides-Extra: ujson
Requires-Dist: attrs (>=21.2.0,<22.0.0)
Requires-Dist: beautifulsoup4 (>=4.9.3,<5.0.0)
Requires-Dist: cattrs (>=1.8.0,<2.0.0)
Requires-Dist: click (>=8.0.1,<9.0.0)
Requires-Dist: openpyxl (>=3.0.7,<4.0.0)
Requires-Dist: python-dateutil (>=2.8.1,<3.0.0)
Requires-Dist: uiautomator2 (>=2.16.7,<3.0.0)
Requires-Dist: ujson (>=4.1.0,<5.0.0); extra == "ujson"
Project-URL: Repository, https://github.com/hexatester/sdgs-tools
